rwend_tools/__init__.py
rwend_tools/custom_logging.py
rwend_tools/google_helpers.py
rwend_tools/utils.py
rwend_tools-1.3.dist-info/METADATA
rwend_tools-1.3.dist-info/WHEEL
rwend_tools-1.3.dist-info/top_level.txt
rwend_tools-1.3.dist-info/RECORD
