Metadata-Version: 2.1
Name: rwend-tools
Version: 1.3
Home-page: https://github.com/rd-wendling/rwend-tools
Author: Ryan Wendling
Requires-Dist: pyyaml
Requires-Dist: googlemaps
Requires-Dist: google-cloud-secret-manager
